sciobject/__init__.py
sciobject/sciobject.py
sciobject/test_sciobject.py
sciobject-0.0.4.dist-info/LICENSE
sciobject-0.0.4.dist-info/METADATA
sciobject-0.0.4.dist-info/WHEEL
sciobject-0.0.4.dist-info/RECORD
